CHANGELOG.txt
LICENCE.txt
MANIFEST.in
README.rst
setup.py
doc/build/_sources/doc.rst.txt
doc/build/_sources/index.rst.txt
doc/source/conf.py
strictdf/__init__.py
strictdf.egg-info/PKG-INFO
strictdf.egg-info/SOURCES.txt
strictdf.egg-info/dependency_links.txt
strictdf.egg-info/requires.txt
strictdf.egg-info/top_level.txt
test/test.py
test/test_main.py