Metadata-Version: 1.1
Name: strictdf
Version: 0.0.15
Summary: A very basic dataframe check
Home-page: UNKNOWN
Author: Test Test
Author-email: testpypi01@gmail.com
License: MIT
Keywords: strictdf
Platform: UNKNOWN
Classifier: Development Status :: 5 - Production/Stable
Classifier: Intended Audience :: Education
Classifier: Operating System :: Microsoft :: Windows :: Windows 10
Classifier: License :: OSI Approved :: MIT License
Classifier: Programming Language :: Python :: 3
